scheduler_front/__init__.py
scheduler_front/app.py
scheduler_front/script_template.py
scheduler_front/static/css/sb-admin.css
scheduler_front/static/css/sb-admin.min.css
scheduler_front/static/js/sb-admin.js
scheduler_front/static/js/sb-admin.min.js
scheduler_front/static/scss/_cards.scss
scheduler_front/static/scss/_footer.scss
scheduler_front/static/scss/_global.scss
scheduler_front/static/scss/_login.scss
scheduler_front/static/scss/_mixins.scss
scheduler_front/static/scss/_navbar.scss
scheduler_front/static/scss/_utilities.scss
scheduler_front/static/scss/_variables.scss
scheduler_front/static/scss/sb-admin.scss
scheduler_front/static/vendor/bootstrap/css/bootstrap-grid.css
scheduler_front/static/vendor/bootstrap/css/bootstrap-grid.min.css
scheduler_front/static/vendor/bootstrap/css/bootstrap-reboot.css
scheduler_front/static/vendor/bootstrap/css/bootstrap-reboot.min.css
scheduler_front/static/vendor/bootstrap/css/bootstrap.css
scheduler_front/static/vendor/bootstrap/css/bootstrap.css.map
scheduler_front/static/vendor/bootstrap/css/bootstrap.min.css
scheduler_front/static/vendor/bootstrap/css/bootstrap.min.css.map
scheduler_front/static/vendor/bootstrap/js/bootstrap.bundle.js
scheduler_front/static/vendor/bootstrap/js/bootstrap.bundle.js.map
scheduler_front/static/vendor/bootstrap/js/bootstrap.bundle.min.js
scheduler_front/static/vendor/bootstrap/js/bootstrap.bundle.min.js.map
scheduler_front/static/vendor/bootstrap/js/bootstrap.js
scheduler_front/static/vendor/bootstrap/js/bootstrap.js.map
scheduler_front/static/vendor/bootstrap/js/bootstrap.min.js
scheduler_front/static/vendor/bootstrap/js/bootstrap.min.js.map
scheduler_front/static/vendor/jquery/jquery.js
scheduler_front/static/vendor/jquery/jquery.min.js
scheduler_front/static/vendor/jquery/jquery.min.map
scheduler_front/static/vendor/jquery/jquery.slim.js
scheduler_front/static/vendor/jquery/jquery.slim.min.js
scheduler_front/static/vendor/jquery/jquery.slim.min.map
scheduler_front-0.0.11.dist-info/METADATA
scheduler_front-0.0.11.dist-info/RECORD
scheduler_front-0.0.11.dist-info/WHEEL
scheduler_front-0.0.11.dist-info/entry_points.txt
scheduler_front-0.0.11.dist-info/top_level.txt
