Metadata-Version: 2.1
Name: scheduler-front
Version: 0.0.11
Summary: Simple library to create scheduled scripts
Home-page: https://gitlab.criteois.com/j.gajardo/scheduler_front
Author: Julio Gajardo
Author-email: j.gajardo@criteo.com
License: MIT
Platform: UNKNOWN
Requires-Dist: flask
